LICENSE
README.md
weevils_cli/__init__.py
weevils_cli/config.py
weevils_cli/entrypoint.py
weevils_cli/exceptions.py
weevils_cli/hosts.py
weevils_cli/jobs.py
weevils_cli/repos.py
weevils_cli/utils.py
weevils_cli/weevils.py
weevils_cli-0.0.2a1.dist-info/METADATA
weevils_cli-0.0.2a1.dist-info/WHEEL
weevils_cli-0.0.2a1.dist-info/LICENSE
weevils_cli-0.0.2a1.dist-info/entry_points.txt
weevils_cli-0.0.2a1.dist-info/RECORD
